colorella/__init__.py
colorella/colormap.py
colorella/conversions.py
colorella/colormaps/Rainbow.json
colorella/colormaps/sgrt_ct_201_ssm_fresh_brownyellowblue.json
colorella/colormaps/sgrt_ct_cont_ssm.json
colorella/colormaps/sgrt_ct_dryfrq.json
colorella/colormaps/sgrt_ct_fldfrq.json
colorella/colormaps/sgrt_ct_rainbow22.json
colorella/colormaps/sgrt_ct_water.json
colorella/colormaps/sgrt_ct_wetfrq.json
colorella-0.0.1.dist-info/AUTHORS.rst
colorella-0.0.1.dist-info/LICENSE.txt
colorella-0.0.1.dist-info/METADATA
colorella-0.0.1.dist-info/WHEEL
colorella-0.0.1.dist-info/top_level.txt
colorella-0.0.1.dist-info/RECORD
